berni/__init__.py
berni/_cutoffs.py
berni/_potentials.py
berni/_schemas.py
berni/f90.py
berni/helpers.py
berni/lammps.py
berni/rumd.py
berni/schema.py
berni/models/bernu_hiwatari_hansen_pastore.json
berni/models/coslovich_pastore-sv1.json
berni/models/coslovich_pastore-sv2.json
berni/models/dellavalle_gazzillo_pastore-sv1.json
berni/models/gaussian_core.json
berni/models/grigera_cavagna_giardina_parisi.json
berni/models/harmonic_spheres.json
berni/models/kob_andersen-sv1.json
berni/models/kob_andersen-sv2.json
berni/models/kob_andersen_2.json
berni/models/lancon_billard_chaudhari.json
berni/models/lennard_jones.json
berni/models/roux_barrat_hansen.json
berni/models/roy_heyde_heuer-II.json
berni/models/roy_heyde_heuer.json
berni/models/wahnstrom.json
berni/samples/bernu_hiwatari_hansen_pastore-f61d7e58b9656cf9640f6e5754441930.json
berni/samples/bernu_hiwatari_hansen_pastore-f61d7e58b9656cf9640f6e5754441930.xyz
berni/samples/coslovich_pastore-488db481cdac35e599922a26129c3e35.json
berni/samples/coslovich_pastore-488db481cdac35e599922a26129c3e35.xyz
berni/samples/grigera_cavagna_giardina_parisi-0ac97fa8c69c320e48bd1fca80855e8a.json
berni/samples/grigera_cavagna_giardina_parisi-0ac97fa8c69c320e48bd1fca80855e8a.xyz
berni/samples/kob_andersen-8f4a9fe755e5c1966c10b50c9a53e6bf.json
berni/samples/kob_andersen-8f4a9fe755e5c1966c10b50c9a53e6bf.xyz
berni/samples/lennard_jones-13ce47602b259f7802e89e23ffd57f19.json
berni/samples/lennard_jones-13ce47602b259f7802e89e23ffd57f19.xyz
berni/samples/lennard_jones-5cc3b80bc415fa5c262e83410ca65779.json
berni/samples/lennard_jones-5cc3b80bc415fa5c262e83410ca65779.xyz
berni/samples/roy_heyde_heuer-II-b8d70742799933357ea83314590d2b4d.json
berni/samples/roy_heyde_heuer-II-b8d70742799933357ea83314590d2b4d.xyz
berni-0.2.0.dist-info/LICENSE
berni-0.2.0.dist-info/METADATA
berni-0.2.0.dist-info/WHEEL
berni-0.2.0.dist-info/top_level.txt
berni-0.2.0.dist-info/RECORD
