Metadata-Version: 2.2
Name: berni
Version: 0.2.0
Summary: Database of interaction models for molecular dynamics and Monte Carlo simulations
Author-email: Daniele Coslovich <daniele.coslovich@umontpellier.fr>
License: GPLv3
Project-URL: repository, https://framagit.org/coslo/berni
Project-URL: homepage, https://framagit.org/coslo/berni
Project-URL: documentation, https://coslo.frama.io/berni
Classifier: License :: OSI Approved :: GNU General Public License v3 (GPLv3)
Classifier: Development Status :: 5 - Production/Stable
Classifier: Programming Language :: Python :: 3
Classifier: Programming Language :: Python :: 3.7
Requires-Python: >=3.7
License-File: LICENSE
Requires-Dist: tinydb
Requires-Dist: jsonschema
Requires-Dist: numpy
